Workbook

Sheet PRODUCTS
A1: PRODUCTS
A2: Happy Hatch data file - written by the forms app. Open it in the app (Open workbook) and entries save into this file.
A4: Product Code | B4: Product Name | C4: Specification | D4: Available Colours | E4: In Stock | F4: Onboard Price | G4: Profitability Percentage | H4: Net Price | I4: Market Price | J4: Revenue | K4: Photo File | L4: Remarks
A5: HH101 | B5: AIR Blower | E5: =SUMIFS(PURCHASE!$E$5:$E$2000,PURCHASE!$C$5:$C$2000,A5)-SUMIFS(SALES_ITEMS!$G$5:$G$2000,SALES_ITEMS!$C$5:$C$2000,A5) | F5: =IF(COUNTIFS(PURCHASE!$C$5:$C$2000,A5,PURCHASE!$E$5:$E$2000,">0")=0,0,IFERROR(LOOKUP(2,1/((PURCHASE!$C$5:$C$2000=A5)*(PURCHASE!$E$5:$E$2000>0)*(PURCHASE!$B$5:$B$2000=SUMPRODUCT(MAX((PURCHASE!$C$5:$C$2000=A5)*(PURCHASE!$E$5:$E$2000>0)*PURCHASE!$B$5:$B$2000)))),PURCHASE!$L$5:$L$2000),0)) | G5: 0.2 | H5: =F5*(1+G5) | J5: =H5-F5 | K5: Product_Photos/HH101.jpg
A6: HH102 | B6: AITOS Whisk | E6: =SUMIFS(PURCHASE!$E$5:$E$2000,PURCHASE!$C$5:$C$2000,A6)-SUMIFS(SALES_ITEMS!$G$5:$G$2000,SALES_ITEMS!$C$5:$C$2000,A6) | F6: =IF(COUNTIFS(PURCHASE!$C$5:$C$2000,A6,PURCHASE!$E$5:$E$2000,">0")=0,0,IFERROR(LOOKUP(2,1/((PURCHASE!$C$5:$C$2000=A6)*(PURCHASE!$E$5:$E$2000>0)*(PURCHASE!$B$5:$B$2000=SUMPRODUCT(MAX((PURCHASE!$C$5:$C$2000=A6)*(PURCHASE!$E$5:$E$2000>0)*PURCHASE!$B$5:$B$2000)))),PURCHASE!$L$5:$L$2000),0)) | G6: 0.2 | H6: =F6*(1+G6) | J6: =H6-F6 | K6: Product_Photos/HH102.jpg
A7: HH103 | B7: Artificial Plant | E7: =SUMIFS(PURCHASE!$E$5:$E$2000,PURCHASE!$C$5:$C$2000,A7)-SUMIFS(SALES_ITEMS!$G$5:$G$2000,SALES_ITEMS!$C$5:$C$2000,A7) | F7: =IF(COUNTIFS(PURCHASE!$C$5:$C$2000,A7,PURCHASE!$E$5:$E$2000,">0")=0,0,IFERROR(LOOKUP(2,1/((PURCHASE!$C$5:$C$2000=A7)*(PURCHASE!$E$5:$E$2000>0)*(PURCHASE!$B$5:$B$2000=SUMPRODUCT(MAX((PURCHASE!$C$5:$C$2000=A7)*(PURCHASE!$E$5:$E$2000>0)*PURCHASE!$B$5:$B$2000)))),PURCHASE!$L$5:$L$2000),0)) | G7: 0.2 | H7: =F7*(1+G7) | J7: =H7-F7 | K7: Product_Photos/HH103.jpg
A8: HH104 | B8: BDO: Storage box Lengthy | D8: Blue, Pink, White | E8: =SUMIFS(PURCHASE!$E$5:$E$2000,PURCHASE!$C$5:$C$2000,A8)-SUMIFS(SALES_ITEMS!$G$5:$G$2000,SALES_ITEMS!$C$5:$C$2000,A8) | F8: =IF(COUNTIFS(PURCHASE!$C$5:$C$2000,A8,PURCHASE!$E$5:$E$2000,">0")=0,0,IFERROR(LOOKUP(2,1/((PURCHASE!$C$5:$C$2000=A8)*(PURCHASE!$E$5:$E$2000>0)*(PURCHASE!$B$5:$B$2000=SUMPRODUCT(MAX((PURCHASE!$C$5:$C$2000=A8)*(PURCHASE!$E$5:$E$2000>0)*PURCHASE!$B$5:$B$2000)))),PURCHASE!$L$5:$L$2000),0)) | G8: 0.2 | H8: =F8*(1+G8) | J8: =H8-F8 | K8: Product_Photos/HH104.jpg
A9: HH105 | B9: BDO: Storage box Wide | D9: Blue, Pink, White | E9: =SUMIFS(PURCHASE!$E$5:$E$2000,PURCHASE!$C$5:$C$2000,A9)-SUMIFS(SALES_ITEMS!$G$5:$G$2000,SALES_ITEMS!$C$5:$C$2000,A9) | F9: =IF(COUNTIFS(PURCHASE!$C$5:$C$2000,A9,PURCHASE!$E$5:$E$2000,">0")=0,0,IFERROR(LOOKUP(2,1/((PURCHASE!$C$5:$C$2000=A9)*(PURCHASE!$E$5:$E$2000>0)*(PURCHASE!$B$5:$B$2000=SUMPRODUCT(MAX((PURCHASE!$C$5:$C$2000=A9)*(PURCHASE!$E$5:$E$2000>0)*PURCHASE!$B$5:$B$2000)))),PURCHASE!$L$5:$L$2000),0)) | G9: 0.2 | H9: =F9*(1+G9) | J9: =H9-F9 | K9: Product_Photos/HH105.jpg
A10: HH106 | B10: BDO: Wave pattern toilet brush | E10: =SUMIFS(PURCHASE!$E$5:$E$2000,PURCHASE!$C$5:$C$2000,A10)-SUMIFS(SALES_ITEMS!$G$5:$G$2000,SALES_ITEMS!$C$5:$C$2000,A10) | F10: =IF(COUNTIFS(PURCHASE!$C$5:$C$2000,A10,PURCHASE!$E$5:$E$2000,">0")=0,0,IFERROR(LOOKUP(2,1/((PURCHASE!$C$5:$C$2000=A10)*(PURCHASE!$E$5:$E$2000>0)*(PURCHASE!$B$5:$B$2000=SUMPRODUCT(MAX((PURCHASE!$C$5:$C$2000=A10)*(PURCHASE!$E$5:$E$2000>0)*PURCHASE!$B$5:$B$2000)))),PURCHASE!$L$5:$L$2000),0)) | G10: 0.2 | H10: =F10*(1+G10) | J10: =H10-F10 | K10: Product_Photos/HH106.jpg
A11: HH107 | B11: Big Basket - White | E11: =SUMIFS(PURCHASE!$E$5:$E$2000,PURCHASE!$C$5:$C$2000,A11)-SUMIFS(SALES_ITEMS!$G$5:$G$2000,SALES_ITEMS!$C$5:$C$2000,A11) | F11: =IF(COUNTIFS(PURCHASE!$C$5:$C$2000,A11,PURCHASE!$E$5:$E$2000,">0")=0,0,IFERROR(LOOKUP(2,1/((PURCHASE!$C$5:$C$2000=A11)*(PURCHASE!$E$5:$E$2000>0)*(PURCHASE!$B$5:$B$2000=SUMPRODUCT(MAX((PURCHASE!$C$5:$C$2000=A11)*(PURCHASE!$E$5:$E$2000>0)*PURCHASE!$B$5:$B$2000)))),PURCHASE!$L$5:$L$2000),0)) | G11: 0.2 | H11: =F11*(1+G11) | J11: =H11-F11 | K11: Product_Photos/HH107.jpg
A12: HH108 | B12: Cheese knife | E12: =SUMIFS(PURCHASE!$E$5:$E$2000,PURCHASE!$C$5:$C$2000,A12)-SUMIFS(SALES_ITEMS!$G$5:$G$2000,SALES_ITEMS!$C$5:$C$2000,A12) | F12: =IF(COUNTIFS(PURCHASE!$C$5:$C$2000,A12,PURCHASE!$E$5:$E$2000,">0")=0,0,IFERROR(LOOKUP(2,1/((PURCHASE!$C$5:$C$2000=A12)*(PURCHASE!$E$5:$E$2000>0)*(PURCHASE!$B$5:$B$2000=SUMPRODUCT(MAX((PURCHASE!$C$5:$C$2000=A12)*(PURCHASE!$E$5:$E$2000>0)*PURCHASE!$B$5:$B$2000)))),PURCHASE!$L$5:$L$2000),0)) | G12: 0.2 | H12: =F12*(1+G12) | J12: =H12-F12 | K12: Product_Photos/HH108.jpg
A13: HH109 | B13: Cleaning cloth | E13: =SUMIFS(PURCHASE!$E$5:$E$2000,PURCHASE!$C$5:$C$2000,A13)-SUMIFS(SALES_ITEMS!$G$5:$G$2000,SALES_ITEMS!$C$5:$C$2000,A13) | F13: =IF(COUNTIFS(PURCHASE!$C$5:$C$2000,A13,PURCHASE!$E$5:$E$2000,">0")=0,0,IFERROR(LOOKUP(2,1/((PURCHASE!$C$5:$C$2000=A13)*(PURCHASE!$E$5:$E$2000>0)*(PURCHASE!$B$5:$B$2000=SUMPRODUCT(MAX((PURCHASE!$C$5:$C$2000=A13)*(PURCHASE!$E$5:$E$2000>0)*PURCHASE!$B$5:$B$2000)))),PURCHASE!$L$5:$L$2000),0)) | G13: 0.2 | H13: =F13*(1+G13) | J13: =H13-F13 | K13: Product_Photos/HH109.jpg
A14: HH110 | B14: Clip | E14: =SUMIFS(PURCHASE!$E$5:$E$2000,PURCHASE!$C$5:$C$2000,A14)-SUMIFS(SALES_ITEMS!$G$5:$G$2000,SALES_ITEMS!$C$5:$C$2000,A14) | F14: =IF(COUNTIFS(PURCHASE!$C$5:$C$2000,A14,PURCHASE!$E$5:$E$2000,">0")=0,0,IFERROR(LOOKUP(2,1/((PURCHASE!$C$5:$C$2000=A14)*(PURCHASE!$E$5:$E$2000>0)*(PURCHASE!$B$5:$B$2000=SUMPRODUCT(MAX((PURCHASE!$C$5:$C$2000=A14)*(PURCHASE!$E$5:$E$2000>0)*PURCHASE!$B$5:$B$2000)))),PURCHASE!$L$5:$L$2000),0)) | G14: 0.2 | H14: =F14*(1+G14) | J14: =H14-F14 | K14: Product_Photos/HH110.jpg
A15: HH111 | B15: Contay - Mini utensil set | E15: =SUMIFS(PURCHASE!$E$5:$E$2000,PURCHASE!$C$5:$C$2000,A15)-SUMIFS(SALES_ITEMS!$G$5:$G$2000,SALES_ITEMS!$C$5:$C$2000,A15) | F15: =IF(COUNTIFS(PURCHASE!$C$5:$C$2000,A15,PURCHASE!$E$5:$E$2000,">0")=0,0,IFERROR(LOOKUP(2,1/((PURCHASE!$C$5:$C$2000=A15)*(PURCHASE!$E$5:$E$2000>0)*(PURCHASE!$B$5:$B$2000=SUMPRODUCT(MAX((PURCHASE!$C$5:$C$2000=A15)*(PURCHASE!$E$5:$E$2000>0)*PURCHASE!$B$5:$B$2000)))),PURCHASE!$L$5:$L$2000),0)) | G15: 0.2 | H15: =F15*(1+G15) | J15: =H15-F15 | K15: Product_Photos/HH111.jpg
A16: HH112 | B16: Cooling towel | E16: =SUMIFS(PURCHASE!$E$5:$E$2000,PURCHASE!$C$5:$C$2000,A16)-SUMIFS(SALES_ITEMS!$G$5:$G$2000,SALES_ITEMS!$C$5:$C$2000,A16) | F16: =IF(COUNTIFS(PURCHASE!$C$5:$C$2000,A16,PURCHASE!$E$5:$E$2000,">0")=0,0,IFERROR(LOOKUP(2,1/((PURCHASE!$C$5:$C$2000=A16)*(PURCHASE!$E$5:$E$2000>0)*(PURCHASE!$B$5:$B$2000=SUMPRODUCT(MAX((PURCHASE!$C$5:$C$2000=A16)*(PURCHASE!$E$5:$E$2000>0)*PURCHASE!$B$5:$B$2000)))),PURCHASE!$L$5:$L$2000),0)) | G16: 0.2 | H16: =F16*(1+G16) | J16: =H16-F16 | K16: Product_Photos/HH112.jpg
A17: HH113 | B17: Crunches | E17: =SUMIFS(PURCHASE!$E$5:$E$2000,PURCHASE!$C$5:$C$2000,A17)-SUMIFS(SALES_ITEMS!$G$5:$G$2000,SALES_ITEMS!$C$5:$C$2000,A17) | F17: =IF(COUNTIFS(PURCHASE!$C$5:$C$2000,A17,PURCHASE!$E$5:$E$2000,">0")=0,0,IFERROR(LOOKUP(2,1/((PURCHASE!$C$5:$C$2000=A17)*(PURCHASE!$E$5:$E$2000>0)*(PURCHASE!$B$5:$B$2000=SUMPRODUCT(MAX((PURCHASE!$C$5:$C$2000=A17)*(PURCHASE!$E$5:$E$2000>0)*PURCHASE!$B$5:$B$2000)))),PURCHASE!$L$5:$L$2000),0)) | G17: 0.2 | H17: =F17*(1+G17) | J17: =H17-F17 | K17: Product_Photos/HH113.jpg
A18: HH114 | B18: Cup Holder | E18: =SUMIFS(PURCHASE!$E$5:$E$2000,PURCHASE!$C$5:$C$2000,A18)-SUMIFS(SALES_ITEMS!$G$5:$G$2000,SALES_ITEMS!$C$5:$C$2000,A18) | F18: =IF(COUNTIFS(PURCHASE!$C$5:$C$2000,A18,PURCHASE!$E$5:$E$2000,">0")=0,0,IFERROR(LOOKUP(2,1/((PURCHASE!$C$5:$C$2000=A18)*(PURCHASE!$E$5:$E$2000>0)*(PURCHASE!$B$5:$B$2000=SUMPRODUCT(MAX((PURCHASE!$C$5:$C$2000=A18)*(PURCHASE!$E$5:$E$2000>0)*PURCHASE!$B$5:$B$2000)))),PURCHASE!$L$5:$L$2000),0)) | G18: 0.2 | H18: =F18*(1+G18) | J18: =H18-F18 | K18: Product_Photos/HH114.jpg
A19: HH115 | B19: DEX - Brush | E19: =SUMIFS(PURCHASE!$E$5:$E$2000,PURCHASE!$C$5:$C$2000,A19)-SUMIFS(SALES_ITEMS!$G$5:$G$2000,SALES_ITEMS!$C$5:$C$2000,A19) | F19: =IF(COUNTIFS(PURCHASE!$C$5:$C$2000,A19,PURCHASE!$E$5:$E$2000,">0")=0,0,IFERROR(LOOKUP(2,1/((PURCHASE!$C$5:$C$2000=A19)*(PURCHASE!$E$5:$E$2000>0)*(PURCHASE!$B$5:$B$2000=SUMPRODUCT(MAX((PURCHASE!$C$5:$C$2000=A19)*(PURCHASE!$E$5:$E$2000>0)*PURCHASE!$B$5:$B$2000)))),PURCHASE!$L$5:$L$2000),0)) | G19: 0.2 | H19: =F19*(1+G19) | J19: =H19-F19 | K19: Product_Photos/HH115.jpg
A20: HH116 | B20: Egg cutter | E20: =SUMIFS(PURCHASE!$E$5:$E$2000,PURCHASE!$C$5:$C$2000,A20)-SUMIFS(SALES_ITEMS!$G$5:$G$2000,SALES_ITEMS!$C$5:$C$2000,A20) | F20: =IF(COUNTIFS(PURCHASE!$C$5:$C$2000,A20,PURCHASE!$E$5:$E$2000,">0")=0,0,IFERROR(LOOKUP(2,1/((PURCHASE!$C$5:$C$2000=A20)*(PURCHASE!$E$5:$E$2000>0)*(PURCHASE!$B$5:$B$2000=SUMPRODUCT(MAX((PURCHASE!$C$5:$C$2000=A20)*(PURCHASE!$E$5:$E$2000>0)*PURCHASE!$B$5:$B$2000)))),PURCHASE!$L$5:$L$2000),0)) | G20: 0.2 | H20: =F20*(1+G20) | J20: =H20-F20 | K20: Product_Photos/HH116.jpg
A21: HH117 | B21: Eye mask | E21: =SUMIFS(PURCHASE!$E$5:$E$2000,PURCHASE!$C$5:$C$2000,A21)-SUMIFS(SALES_ITEMS!$G$5:$G$2000,SALES_ITEMS!$C$5:$C$2000,A21) | F21: =IF(COUNTIFS(PURCHASE!$C$5:$C$2000,A21,PURCHASE!$E$5:$E$2000,">0")=0,0,IFERROR(LOOKUP(2,1/((PURCHASE!$C$5:$C$2000=A21)*(PURCHASE!$E$5:$E$2000>0)*(PURCHASE!$B$5:$B$2000=SUMPRODUCT(MAX((PURCHASE!$C$5:$C$2000=A21)*(PURCHASE!$E$5:$E$2000>0)*PURCHASE!$B$5:$B$2000)))),PURCHASE!$L$5:$L$2000),0)) | G21: 0.2 | H21: =F21*(1+G21) | J21: =H21-F21 | K21: Product_Photos/HH117.jpg
... A46: HH142 | B46: White plastic basket | E46: =SUMIFS(PURCHASE!$E$5:$E$2000,PURCHASE!$C$5:$C$2000,A46)-SUMIFS(SALES_ITEMS!$G$5:$G$2000,SALES_ITEMS!$C$5:$C$2000,A46) | F46: =IF(COUNTIFS(PURCHASE!$C$5:$C$2000,A46,PURCHASE!$E$5:$E$2000,">0")=0,0,IFERROR(LOOKUP(2,1/((PURCHASE!$C$5:$C$2000=A46)*(PURCHASE!$E$5:$E$2000>0)*(PURCHASE!$B$5:$B$2000=SUMPRODUCT(MAX((PURCHASE!$C$5:$C$2000=A46)*(PURCHASE!$E$5:$E$2000>0)*PURCHASE!$B$5:$B$2000)))),PURCHASE!$L$5:$L$2000),0)) | G46: 0.2 | H46: =F46*(1+G46) | J46: =H46-F46 | K46: Product_Photos/HH142.jpg

Sheet SALES
A1: SALES
A2: Happy Hatch data file - written by the forms app. One row per sales order (header).
A4: Order Number | B4: Date of Sale | C4: Customer Number | D4: Tax Code | E4: GST (%) | F4: CGST (%) | G4: SGST (%) | H4: IGST (%) | I4: Sub Total | J4: Tax Amount | K4: Total Amount | L4: Invoice No. | M4: Remarks

Sheet SALES_ITEMS
A1: SALES_ITEMS
A2: Happy Hatch data file - written by the forms app. One row per product on an order (linked by Order Number).
A4: Order Number | B4: Date of Sale | C4: Product Code | D4: Product Name | E4: Product price | F4: MRP | G4: Quantity | H4: Unit | I4: Net Amount | J4: Colour | K4: Remarks

Sheet CUSTOMERS
A1: CUSTOMERS
A2: Happy Hatch data file - written by the forms app. Open it in the app (Open workbook) and entries save into this file.
A4: Customer Number | B4: Customer Name | C4: Contact Person | D4: Phone | E4: Email | F4: Address | G4: City | H4: Remarks

Sheet PURCHASE
A1: PURCHASE
A2: Happy Hatch data file - written by the forms app. Open it in the app (Open workbook) and entries save into this file.
A4: Purchase Number | B4: Date of Purchase | C4: Product Code | D4: Product Name | E4: Quantity | F4: Unit | G4: Unit Cost | H4: Total Unit Price | I4: Freight Charges | J4: Other Charges | K4: Total Cost | L4: Onboard Price/Unit | M4: Shipper Number | N4: Shipper Name | O4: Shipper Contact | P4: Shipper Email | Q4: Remarks
A5: PUR-001 | B5: 46319 | C5: HH101 | D5: =IFERROR(INDEX(PRODUCTS!$B$5:$B$2000,MATCH(C5,PRODUCTS!$A$5:$A$2000,0)),"") | E5: 6 | F5: Pcs | G5: 1 | H5: 6 | K5: =H5+I5+J5 | L5: =IF(E5>0,K5/E5,0) | N5: =IFERROR(INDEX(SHIPPER!$B$5:$B$2000,MATCH(M5,SHIPPER!$A$5:$A$2000,0)),"") | O5: =IFERROR(INDEX(SHIPPER!$D$5:$D$2000,MATCH(M5,SHIPPER!$A$5:$A$2000,0)),"") | P5: =IFERROR(INDEX(SHIPPER!$E$5:$E$2000,MATCH(M5,SHIPPER!$A$5:$A$2000,0)),"")
A6: PUR-002 | B6: 46319 | C6: HH102 | D6: =IFERROR(INDEX(PRODUCTS!$B$5:$B$2000,MATCH(C6,PRODUCTS!$A$5:$A$2000,0)),"") | E6: 16 | F6: Pcs | G6: 1 | H6: 16 | K6: =H6+I6+J6 | L6: =IF(E6>0,K6/E6,0) | N6: =IFERROR(INDEX(SHIPPER!$B$5:$B$2000,MATCH(M6,SHIPPER!$A$5:$A$2000,0)),"") | O6: =IFERROR(INDEX(SHIPPER!$D$5:$D$2000,MATCH(M6,SHIPPER!$A$5:$A$2000,0)),"") | P6: =IFERROR(INDEX(SHIPPER!$E$5:$E$2000,MATCH(M6,SHIPPER!$A$5:$A$2000,0)),"")
A7: PUR-003 | B7: 46319 | C7: HH103 | D7: =IFERROR(INDEX(PRODUCTS!$B$5:$B$2000,MATCH(C7,PRODUCTS!$A$5:$A$2000,0)),"") | E7: 24 | F7: Pcs | G7: 1 | H7: 24 | K7: =H7+I7+J7 | L7: =IF(E7>0,K7/E7,0) | N7: =IFERROR(INDEX(SHIPPER!$B$5:$B$2000,MATCH(M7,SHIPPER!$A$5:$A$2000,0)),"") | O7: =IFERROR(INDEX(SHIPPER!$D$5:$D$2000,MATCH(M7,SHIPPER!$A$5:$A$2000,0)),"") | P7: =IFERROR(INDEX(SHIPPER!$E$5:$E$2000,MATCH(M7,SHIPPER!$A$5:$A$2000,0)),"")
A8: PUR-004 | B8: 46319 | C8: HH104 | D8: =IFERROR(INDEX(PRODUCTS!$B$5:$B$2000,MATCH(C8,PRODUCTS!$A$5:$A$2000,0)),"") | E8: 12 | F8: Pcs | G8: 1 | H8: 12 | K8: =H8+I8+J8 | L8: =IF(E8>0,K8/E8,0) | N8: =IFERROR(INDEX(SHIPPER!$B$5:$B$2000,MATCH(M8,SHIPPER!$A$5:$A$2000,0)),"") | O8: =IFERROR(INDEX(SHIPPER!$D$5:$D$2000,MATCH(M8,SHIPPER!$A$5:$A$2000,0)),"") | P8: =IFERROR(INDEX(SHIPPER!$E$5:$E$2000,MATCH(M8,SHIPPER!$A$5:$A$2000,0)),"")
A9: PUR-005 | B9: 46319 | C9: HH105 | D9: =IFERROR(INDEX(PRODUCTS!$B$5:$B$2000,MATCH(C9,PRODUCTS!$A$5:$A$2000,0)),"") | E9: 15 | F9: Pcs | G9: 1 | H9: 15 | K9: =H9+I9+J9 | L9: =IF(E9>0,K9/E9,0) | N9: =IFERROR(INDEX(SHIPPER!$B$5:$B$2000,MATCH(M9,SHIPPER!$A$5:$A$2000,0)),"") | O9: =IFERROR(INDEX(SHIPPER!$D$5:$D$2000,MATCH(M9,SHIPPER!$A$5:$A$2000,0)),"") | P9: =IFERROR(INDEX(SHIPPER!$E$5:$E$2000,MATCH(M9,SHIPPER!$A$5:$A$2000,0)),"")
A10: PUR-006 | B10: 46319 | C10: HH106 | D10: =IFERROR(INDEX(PRODUCTS!$B$5:$B$2000,MATCH(C10,PRODUCTS!$A$5:$A$2000,0)),"") | E10: 6 | F10: Pcs | G10: 1 | H10: 6 | K10: =H10+I10+J10 | L10: =IF(E10>0,K10/E10,0) | N10: =IFERROR(INDEX(SHIPPER!$B$5:$B$2000,MATCH(M10,SHIPPER!$A$5:$A$2000,0)),"") | O10: =IFERROR(INDEX(SHIPPER!$D$5:$D$2000,MATCH(M10,SHIPPER!$A$5:$A$2000,0)),"") | P10: =IFERROR(INDEX(SHIPPER!$E$5:$E$2000,MATCH(M10,SHIPPER!$A$5:$A$2000,0)),"")
A11: PUR-007 | B11: 46319 | C11: HH107 | D11: =IFERROR(INDEX(PRODUCTS!$B$5:$B$2000,MATCH(C11,PRODUCTS!$A$5:$A$2000,0)),"") | E11: 6 | F11: Pcs | G11: 1 | H11: 6 | K11: =H11+I11+J11 | L11: =IF(E11>0,K11/E11,0) | N11: =IFERROR(INDEX(SHIPPER!$B$5:$B$2000,MATCH(M11,SHIPPER!$A$5:$A$2000,0)),"") | O11: =IFERROR(INDEX(SHIPPER!$D$5:$D$2000,MATCH(M11,SHIPPER!$A$5:$A$2000,0)),"") | P11: =IFERROR(INDEX(SHIPPER!$E$5:$E$2000,MATCH(M11,SHIPPER!$A$5:$A$2000,0)),"")
A12: PUR-008 | B12: 46319 | C12: HH108 | D12: =IFERROR(INDEX(PRODUCTS!$B$5:$B$2000,MATCH(C12,PRODUCTS!$A$5:$A$2000,0)),"") | E12: 12 | F12: Pcs | G12: 1 | H12: 12 | K12: =H12+I12+J12 | L12: =IF(E12>0,K12/E12,0) | N12: =IFERROR(INDEX(SHIPPER!$B$5:$B$2000,MATCH(M12,SHIPPER!$A$5:$A$2000,0)),"") | O12: =IFERROR(INDEX(SHIPPER!$D$5:$D$2000,MATCH(M12,SHIPPER!$A$5:$A$2000,0)),"") | P12: =IFERROR(INDEX(SHIPPER!$E$5:$E$2000,MATCH(M12,SHIPPER!$A$5:$A$2000,0)),"")
A13: PUR-009 | B13: 46319 | C13: HH109 | D13: =IFERROR(INDEX(PRODUCTS!$B$5:$B$2000,MATCH(C13,PRODUCTS!$A$5:$A$2000,0)),"") | E13: 30 | F13: Pcs | G13: 1 | H13: 30 | K13: =H13+I13+J13 | L13: =IF(E13>0,K13/E13,0) | N13: =IFERROR(INDEX(SHIPPER!$B$5:$B$2000,MATCH(M13,SHIPPER!$A$5:$A$2000,0)),"") | O13: =IFERROR(INDEX(SHIPPER!$D$5:$D$2000,MATCH(M13,SHIPPER!$A$5:$A$2000,0)),"") | P13: =IFERROR(INDEX(SHIPPER!$E$5:$E$2000,MATCH(M13,SHIPPER!$A$5:$A$2000,0)),"")
A14: PUR-010 | B14: 46319 | C14: HH110 | D14: =IFERROR(INDEX(PRODUCTS!$B$5:$B$2000,MATCH(C14,PRODUCTS!$A$5:$A$2000,0)),"") | E14: 2 | F14: Kg | G14: 1 | H14: 2 | K14: =H14+I14+J14 | L14: =IF(E14>0,K14/E14,0) | N14: =IFERROR(INDEX(SHIPPER!$B$5:$B$2000,MATCH(M14,SHIPPER!$A$5:$A$2000,0)),"") | O14: =IFERROR(INDEX(SHIPPER!$D$5:$D$2000,MATCH(M14,SHIPPER!$A$5:$A$2000,0)),"") | P14: =IFERROR(INDEX(SHIPPER!$E$5:$E$2000,MATCH(M14,SHIPPER!$A$5:$A$2000,0)),"")
A15: PUR-011 | B15: 46319 | C15: HH111 | D15: =IFERROR(INDEX(PRODUCTS!$B$5:$B$2000,MATCH(C15,PRODUCTS!$A$5:$A$2000,0)),"") | E15: 6 | F15: Pcs | G15: 1 | H15: 6 | K15: =H15+I15+J15 | L15: =IF(E15>0,K15/E15,0) | N15: =IFERROR(INDEX(SHIPPER!$B$5:$B$2000,MATCH(M15,SHIPPER!$A$5:$A$2000,0)),"") | O15: =IFERROR(INDEX(SHIPPER!$D$5:$D$2000,MATCH(M15,SHIPPER!$A$5:$A$2000,0)),"") | P15: =IFERROR(INDEX(SHIPPER!$E$5:$E$2000,MATCH(M15,SHIPPER!$A$5:$A$2000,0)),"")
A16: PUR-012 | B16: 46319 | C16: HH112 | D16: =IFERROR(INDEX(PRODUCTS!$B$5:$B$2000,MATCH(C16,PRODUCTS!$A$5:$A$2000,0)),"") | E16: 12 | F16: Pcs | G16: 1 | H16: 12 | K16: =H16+I16+J16 | L16: =IF(E16>0,K16/E16,0) | N16: =IFERROR(INDEX(SHIPPER!$B$5:$B$2000,MATCH(M16,SHIPPER!$A$5:$A$2000,0)),"") | O16: =IFERROR(INDEX(SHIPPER!$D$5:$D$2000,MATCH(M16,SHIPPER!$A$5:$A$2000,0)),"") | P16: =IFERROR(INDEX(SHIPPER!$E$5:$E$2000,MATCH(M16,SHIPPER!$A$5:$A$2000,0)),"")
... A46: PUR-042 | B46: 46319 | C46: HH142 | D46: =IFERROR(INDEX(PRODUCTS!$B$5:$B$2000,MATCH(C46,PRODUCTS!$A$5:$A$2000,0)),"") | E46: 6 | F46: Pcs | G46: 1 | H46: 6 | K46: =H46+I46+J46 | L46: =IF(E46>0,K46/E46,0) | N46: =IFERROR(INDEX(SHIPPER!$B$5:$B$2000,MATCH(M46,SHIPPER!$A$5:$A$2000,0)),"") | O46: =IFERROR(INDEX(SHIPPER!$D$5:$D$2000,MATCH(M46,SHIPPER!$A$5:$A$2000,0)),"") | P46: =IFERROR(INDEX(SHIPPER!$E$5:$E$2000,MATCH(M46,SHIPPER!$A$5:$A$2000,0)),"")

Sheet SHIPPER
A1: SHIPPER
A2: Shipper details used by the Purchase sheet: pick a Shipper Number on each purchase and the name, contact and e-mail fill in.
A4: Shipper Number | B4: Shipper Name | C4: Contact Person | D4: Phone | E4: Email | F4: Address | G4: City | H4: Remarks

Sheet TAX
A1: TAX
A2: Tax rates used by the Sales sheet: pick a Tax Code on each sale and its GST / CGST / SGST / IGST (%) are applied.
A4: Tax Code | B4: Tax Name | C4: GST (%) | D4: CGST (%) | E4: SGST (%) | F4: IGST (%) | G4: Remarks

Sheet _ADMIN_SCHEMA
A1: Sheet | B1: Column | C1: Type | D1: Required | E1: Unique | F1: Default | G1: Options | H1: Formula
